powerplayer.py
powerplayer-0.2.1.dist-info/entry_points.txt
powerplayer-0.2.1.dist-info/LICENSE.MD
powerplayer-0.2.1.dist-info/WHEEL
powerplayer-0.2.1.dist-info/METADATA
powerplayer-0.2.1.dist-info/RECORD
