Metadata-Version: 2.1
Name: powerplayer
Version: 0.2.1
Summary: A command line interface to play music
Home-page: https://github.com/AvanindraC/Powerplayer
License: MIT
Author: Avanindra Chakraborty
Requires-Python: >=3.7,<4.0
Classifier: License :: OSI Approved :: MIT License
Classifier: Operating System :: OS Independent
Classifier: Programming Language :: Python :: 3
Classifier: Programming Language :: Python :: 3.10
Classifier: Programming Language :: Python :: 3.6
Classifier: Programming Language :: Python :: 3.7
Classifier: Programming Language :: Python :: 3.8
Classifier: Programming Language :: Python :: 3.9
Requires-Dist: bs4 (>=0.0.1,<0.0.2)
Requires-Dist: click (>=8.0.1,<9.0.0)
Requires-Dist: click-help-colors (>=0.9.1,<0.10.0)
Requires-Dist: playsound (>=1.2.2,<2.0.0)
Requires-Dist: python-vlc (>=3.0.12118,<4.0.0)
Requires-Dist: requests (>=2.25.1,<3.0.0)
Requires-Dist: youtube-search (>=2.1.0,<3.0.0)
Requires-Dist: youtube_dl (>=2021.6.6,<2022.0.0)
Project-URL: Repository, https://github.com/AvanindraC/Powerplayer
